[
	{
		"slot": "weapon",
		"limit": -1
	},
	{
		"slot": "offhand",
		"limit": -1
	},
	{
		"slot": "tool",
		"limit": -1
	},
	{
		"slot": "friend",
		"limit": -1
	},
	{
		"slot": "neck",
		"limit": 3
	},
	{
		"slot": "hat",
		"limit": 1
	},
	{
		"slot": "coat",
		"limit": 1
	},
	{
		"slot": "pants",
		"limit": 1
	},
	{
		"slot": "shoulders",
		"limit": 1
	},
	{
		"slot": "shoes",
		"limit": 1
	},
	{
		"slot": "face",
		"limit": 1
	},
	{
		"slot": "ring",
		"limit": 4
	},
	{
		"slot": "belt",
		"limit": 3
	},
	{
		"slot": "shirt",
		"limit": 1
	}
]